majava/__init__.py
majava/basic.py
majava/formats.py
majava/fs.py
majava/matchers.py
majava/pytplug.py
majava-0.3.0.dist-info/METADATA
majava-0.3.0.dist-info/WHEEL
majava-0.3.0.dist-info/entry_points.txt
majava-0.3.0.dist-info/top_level.txt
majava-0.3.0.dist-info/RECORD
