Metadata-Version: 2.2
Name: majava
Version: 0.3.0
Summary: Collection of matchers for testing
Author: wsnk
License: MIT
Project-URL: Homepage, https://github.com/wsnk/majava
Keywords: testing,test,pytest,matcher
Requires-Dist: pytest
Provides-Extra: tests
Requires-Dist: flake8; extra == "tests"
